flypool/__init__.py
flypool/__main__.py
flypool/ethermine.py
flypool/ravencoin.py
flypool/utils.py
flypool_cli-1.0.0.dist-info/METADATA
flypool_cli-1.0.0.dist-info/WHEEL
flypool_cli-1.0.0.dist-info/entry_points.txt
flypool_cli-1.0.0.dist-info/top_level.txt
flypool_cli-1.0.0.dist-info/RECORD
