Metadata-Version: 2.1
Name: flypool-cli
Version: 1.0.0
Summary: A command-line tool for monitoring the status on flypools(ether and raven).
Home-page: https://github.com/KohakuBlueleaf/ethermine_cli
Author: BlueLeaf
Author-email: apolloyeh0123@gmail.com
License: UNKNOWN
Platform: UNKNOWN
Requires-Dist: requests
